pytest_pyramid/__init__.py
pytest_pyramid/factories.py
pytest_pyramid/plugin.py
pytest_pyramid-1.1.0.dist-info/licenses/LICENSE
pytest_pyramid-1.1.0.dist-info/METADATA
pytest_pyramid-1.1.0.dist-info/WHEEL
pytest_pyramid-1.1.0.dist-info/entry_points.txt
pytest_pyramid-1.1.0.dist-info/top_level.txt
pytest_pyramid-1.1.0.dist-info/zip-safe
pytest_pyramid-1.1.0.dist-info/RECORD
