Metadata-Version: 2.4
Name: pytest_pyramid
Version: 1.1.0
Summary: pytest_pyramid - provides fixtures for testing pyramid applications with pytest test suite
Author-email: Grzegorz Śliwiński <fizyk+pypi@fizyk.dev>
License: The MIT License (MIT): http://opensource.org/licenses/MIT
Project-URL: Source, https://github.com/fizyk/pytest_pyramid/
Project-URL: Bug Tracker, https://github.com/fizyk/pytest_pyramid/issues
Project-URL: Changelog, https://github.com/fizyk/pytest_pyramid/blob/v1.1.0/CHANGES.rst
Keywords: pyramid,pytest,testing
Classifier: Development Status :: 5 - Production/Stable
Classifier: Environment :: Plugins
Classifier: Environment :: Web Environment
Classifier: Intended Audience :: Developers
Classifier: License :: OSI Approved :: MIT License
Classifier: Natural Language :: English
Classifier: Operating System :: OS Independent
Classifier: Programming Language :: Python
Classifier: Programming Language :: Python :: 3
Classifier: Programming Language :: Python :: 3.10
Classifier: Programming Language :: Python :: 3.11
Classifier: Programming Language :: Python :: 3.12
Classifier: Programming Language :: Python :: 3.13
Classifier: Programming Language :: Python :: 3.14
Classifier: Framework :: Pyramid
Classifier: Framework :: Pytest
Classifier: Topic :: Software Development :: Libraries :: Python Modules
Classifier: Topic :: Software Development :: Testing
Classifier: Topic :: Software Development :: Testing :: Unit
Requires-Python: >=3.10
License-File: LICENSE
Requires-Dist: pytest
Requires-Dist: pyramid
Requires-Dist: webtest
Dynamic: license-file
